arabic_translator_tester/__init__.py
arabic_translator_tester/main.py
arabic_translator_tester/pipeline/__init__.py
arabic_translator_tester/pipeline/voice_translate.py
arabic_translator_tester/translator/__init__.py
arabic_translator_tester/translator/argos.py
arabic_translator_tester/voice/__init__.py
arabic_translator_tester/voice/mic.py
arabic_translator_tester/voice/stt_vosk.py
arabic_translator_tester-0.1.8.dist-info/METADATA
arabic_translator_tester-0.1.8.dist-info/WHEEL
arabic_translator_tester-0.1.8.dist-info/entry_points.txt
arabic_translator_tester-0.1.8.dist-info/licenses/LICENSE
arabic_translator_tester-0.1.8.dist-info/RECORD
