Metadata-Version: 2.4
Name: arabic-translator-tester
Version: 0.1.8
Summary: Offline Arabic voice-to-English translator using Vosk and Argos Translate
License: MIT License
License-File: LICENSE
Classifier: License :: OSI Approved :: MIT License
Classifier: Operating System :: OS Independent
Classifier: Programming Language :: Python :: 3
Classifier: Programming Language :: Python :: 3.12
Requires-Python: >=3.9
Requires-Dist: argostranslate>=1.9.0
Requires-Dist: numpy>=1.26
Requires-Dist: sounddevice>=0.4.6
Requires-Dist: vosk>=0.3.45
